Metadata-Version: 1.1
Name: cryptowatch-client
Version: 0.1.3
Summary: cryptowatch-client is a python client library for cryptowatch public market rest api
Home-page: https://github.com/10mohi6/cryptowatch-api-python-client
Author: 10mohi6
Author-email: 10.mohi.6.y@gmail.com
License: MIT
Keywords: cryptowatch
Platform: UNKNOWN
Classifier: Development Status :: 4 - Beta
Classifier: Programming Language :: Python :: 3.6
Classifier: Intended Audience :: Financial and Insurance Industry
Classifier: Intended Audience :: Developers
Classifier: Intended Audience :: Information Technology
Classifier: Operating System :: OS Independent
Classifier: Topic :: Software Development :: Build Tools
Classifier: Topic :: Office/Business :: Financial :: Investment
Classifier: License :: OSI Approved :: MIT License
